deepseek_cli/__init__.py
deepseek_cli/api.py
deepseek_cli/cli.py
deepseek_cli/config.py
deepseek_cli/formatter.py
deepseek_cli_pro-0.2.1.dist-info/LICENSE
deepseek_cli_pro-0.2.1.dist-info/METADATA
deepseek_cli_pro-0.2.1.dist-info/WHEEL
deepseek_cli_pro-0.2.1.dist-info/entry_points.txt
deepseek_cli_pro-0.2.1.dist-info/top_level.txt
deepseek_cli_pro-0.2.1.dist-info/RECORD
