Metadata-Version: 2.2
Name: deepseek-cli-pro
Version: 0.2.1
Summary: Rich-powered CLI interface for DeepSeek AI models
Author-email: Sifat Hasan <sihabhossan633@gmail.com>
License: MIT
Project-URL: Homepage, https://github.com/Pro-Sifat-Hasan/deepseek-cli
Classifier: License :: OSI Approved :: MIT License
Classifier: Programming Language :: Python :: 3
Classifier: Operating System :: OS Independent
Requires-Python: >=3.8
License-File: LICENSE
Requires-Dist: rich>=13.0.0
Requires-Dist: click>=8.0.0
Requires-Dist: openai>=1.0.0
